Makefile
README.rst
setup.py
docs/Makefile
docs/make.bat
docs/source/HISTORY.rst
docs/source/README.rst
docs/source/api.rst
docs/source/conf.py
docs/source/index.rst
scripts/api-sample.py
scripts/out.txt
scripts/sample.zip
xmldirector/__init__.py
xmldirector.dropbox.egg-info/PKG-INFO
xmldirector.dropbox.egg-info/SOURCES.txt
xmldirector.dropbox.egg-info/dependency_links.txt
xmldirector.dropbox.egg-info/entry_points.txt
xmldirector.dropbox.egg-info/namespace_packages.txt
xmldirector.dropbox.egg-info/not-zip-safe
xmldirector.dropbox.egg-info/requires.txt
xmldirector.dropbox.egg-info/top_level.txt
xmldirector/dropbox/__init__.py
xmldirector/dropbox/configure.zcml
xmldirector/dropbox/header.txt
xmldirector/dropbox/i18n.py
xmldirector/dropbox/interfaces.py
xmldirector/dropbox/logger.py
xmldirector/dropbox/profiles-4.zcml
xmldirector/dropbox/profiles-5.zcml
xmldirector/dropbox/browser/__init__.py
xmldirector/dropbox/browser/configure.zcml
xmldirector/dropbox/browser/controlpanel.py
xmldirector/dropbox/browser/dropbox_authentication.pt
xmldirector/dropbox/browser/dropbox_authentication.py
xmldirector/dropbox/browser/dropboxfs.py
xmldirector/dropbox/browser/resources/dropbox.svg
xmldirector/dropbox/browser/resources/local.js
xmldirector/dropbox/locales/LC_MESSAGES/de/README.txt
xmldirector/dropbox/profiles/common/README.txt
xmldirector/dropbox/profiles/common/browserlayer.xml
xmldirector/dropbox/profiles/common/controlpanel.xml
xmldirector/dropbox/profiles/common/metadata.xml
xmldirector/dropbox/profiles/common/registry.xml
xmldirector/dropbox/profiles/common/types.xml
xmldirector/dropbox/profiles/common/types/xmldirector.plonecore.connector.xml
xmldirector/dropbox/profiles/plone-4/cssregistry.xml
xmldirector/dropbox/profiles/plone-4/metadata.xml
xmldirector/dropbox/profiles/plone-5/metadata.xml
xmldirector/dropbox/profiles/plone-5/registry.xml