Metadata-Version: 1.1
Name: xmldirector.dropbox
Version: 1.0.0
Summary: Plone XML-Director integration with Dropbox
Home-page: http://pypi.python.org/pypi/xmldirector.dropbox
Author: Andreas Jung
Author-email: info@zopyx.com
License: GPL
Keywords: xml-director dropbox XML Plone Python
Platform: UNKNOWN
Classifier: Programming Language :: Python
Classifier: Framework :: Plone
Classifier: Framework :: Plone :: 4.3
Classifier: Framework :: Plone :: 5.0
Classifier: Framework :: Zope2
Classifier: Topic :: Software Development :: Libraries :: Python Modules
